{
  "generated_at": "2026-06-29 06:45:35",
  "stocks": [
    {
      "symbol": "002734",
      "price": 17.1,
      "change_pct": -3.99,
      "volume": 161555,
      "rsi": 55.63,
      "ma20": 16.93,
      "last_5_days": [
        19.1,
        18.96,
        18.28,
        17.81,
        17.1
      ],
      "volume_price_signal": "价跌量缩（抛压减轻）",
      "main_force_signal": "震荡整理（方向待明）",
      "name": "未知名称",
      "analysis": "API错误(403)"
    },
    {
      "symbol": "600722",
      "price": 8.15,
      "change_pct": -0.61,
      "volume": 213881,
      "rsi": 30.83,
      "ma20": 9.53,
      "last_5_days": [
        9.14,
        8.68,
        8.49,
        8.2,
        8.15
      ],
      "volume_price_signal": "价跌量缩（抛压减轻）",
      "main_force_signal": "震荡整理（方向待明）",
      "name": "未知名称",
      "analysis": "API错误(403)"
    },
    {
      "symbol": "300170",
      "price": 14.86,
      "change_pct": -1.72,
      "volume": 411958,
      "rsi": 29.45,
      "ma20": 17.58,
      "last_5_days": [
        17.2,
        17.14,
        16.33,
        15.12,
        14.86
      ],
      "volume_price_signal": "价跌量缩（抛压减轻）",
      "main_force_signal": "震荡整理（方向待明）",
      "name": "未知名称",
      "analysis": "API错误(403)"
    },
    {
      "symbol": "300548",
      "price": 251.24,
      "change_pct": -4.34,
      "volume": 133551,
      "rsi": 60.15,
      "ma20": 252.2,
      "last_5_days": [
        286.02,
        282.23,
        281.9,
        262.65,
        251.24
      ],
      "volume_price_signal": "价跌量缩（抛压减轻）",
      "main_force_signal": "震荡整理（方向待明）",
      "name": "未知名称",
      "analysis": "API错误(403)"
    },
    {
      "symbol": "301377",
      "price": 553.6,
      "change_pct": -6.17,
      "volume": 79039,
      "rsi": 64.7,
      "ma20": 501.55,
      "last_5_days": [
        600.0,
        620.0,
        640.5,
        590.0,
        553.6
      ],
      "volume_price_signal": "放量下跌（主力出货或洗盘）",
      "main_force_signal": "震荡整理（方向待明）",
      "name": "未知名称",
      "analysis": "API错误(403)"
    },
    {
      "symbol": "003031",
      "price": 169.5,
      "change_pct": -7.43,
      "volume": 158660,
      "rsi": 65.87,
      "ma20": 159.42,
      "last_5_days": [
        187.44,
        194.0,
        195.57,
        183.1,
        169.5
      ],
      "volume_price_signal": "放量下跌（主力出货或洗盘）",
      "main_force_signal": "震荡整理（方向待明）",
      "name": "未知名称",
      "analysis": "API错误(403)"
    },
    {
      "symbol": "301338",
      "price": 152.2,
      "change_pct": -2.85,
      "volume": 66815,
      "rsi": 42.62,
      "ma20": 163.73,
      "last_5_days": [
        155.5,
        167.9,
        172.65,
        156.66,
        152.2
      ],
      "volume_price_signal": "价跌量缩（抛压减轻）",
      "main_force_signal": "震荡整理（方向待明）",
      "name": "未知名称",
      "analysis": "API错误(403)"
    },
    {
      "symbol": "301035",
      "price": 46.5,
      "change_pct": 1.93,
      "volume": 16702,
      "rsi": 36.05,
      "ma20": 50.2,
      "last_5_days": [
        48.2,
        48.3,
        46.82,
        45.62,
        46.5
      ],
      "volume_price_signal": "价涨量增（趋势健康）",
      "main_force_signal": "震荡整理（方向待明）",
      "name": "未知名称",
      "analysis": "API错误(403)"
    },
    {
      "symbol": "300620",
      "price": 362.49,
      "change_pct": 0.02,
      "volume": 137989,
      "rsi": 63.49,
      "ma20": 343.7,
      "last_5_days": [
        384.52,
        406.0,
        395.46,
        362.43,
        362.49
      ],
      "volume_price_signal": "缩量上涨（持续性存疑）",
      "main_force_signal": "震荡整理（方向待明）",
      "name": "未知名称",
      "analysis": "API错误(403)"
    },
    {
      "symbol": "301183",
      "price": 238.5,
      "change_pct": -2.13,
      "volume": 63006,
      "rsi": 65.03,
      "ma20": 233.57,
      "last_5_days": [
        248.61,
        258.9,
        260.05,
        243.7,
        238.5
      ],
      "volume_price_signal": "价跌量缩（抛压减轻）",
      "main_force_signal": "震荡整理（方向待明）",
      "name": "未知名称",
      "analysis": "API错误(403)"
    },
    {
      "symbol": "300757",
      "price": 578.34,
      "change_pct": -1.63,
      "volume": 58550,
      "rsi": 45.55,
      "ma20": 627.83,
      "last_5_days": [
        578.2,
        602.5,
        647.0,
        587.9,
        578.34
      ],
      "volume_price_signal": "价跌量缩（抛压减轻）",
      "main_force_signal": "低位吸筹（横盘缩量）",
      "name": "未知名称",
      "analysis": "API错误(403)"
    },
    {
      "symbol": "300308",
      "price": 1218.99,
      "change_pct": -2.78,
      "volume": 339497,
      "rsi": 56.04,
      "ma20": 1237.48,
      "last_5_days": [
        1310.01,
        1312.18,
        1323.4,
        1253.89,
        1218.99
      ],
      "volume_price_signal": "价跌量缩（抛压减轻）",
      "main_force_signal": "震荡整理（方向待明）",
      "name": "未知名称",
      "analysis": "API错误(403)"
    },
    {
      "symbol": "000001",
      "price": 10.23,
      "change_pct": 0.0,
      "volume": 1067352,
      "rsi": 39.0,
      "ma20": 10.68,
      "last_5_days": [
        10.71,
        10.51,
        10.42,
        10.23,
        10.23
      ],
      "volume_price_signal": "价跌量缩（抛压减轻）",
      "main_force_signal": "震荡整理（方向待明）",
      "name": "未知名称",
      "analysis": "API错误(403)"
    },
    {
      "symbol": "399006",
      "price": 4209.3,
      "change_pct": 0.36,
      "volume": 237019489,
      "rsi": 64.31,
      "ma20": 4079.05,
      "last_5_days": [
        4192.19,
        4251.42,
        4371.99,
        4194.21,
        4209.3
      ],
      "volume_price_signal": "缩量上涨（持续性存疑）",
      "main_force_signal": "低位吸筹（横盘缩量）",
      "name": "未知名称",
      "analysis": "API错误(403)"
    },
    {
      "symbol": "399106",
      "price": 2776.76,
      "change_pct": -0.33,
      "volume": 760811120,
      "rsi": 58.61,
      "ma20": 2788.62,
      "last_5_days": [
        2833.77,
        2855.61,
        2876.11,
        2786.04,
        2776.76
      ],
      "volume_price_signal": "价跌量缩（抛压减轻）",
      "main_force_signal": "震荡整理（方向待明）",
      "name": "未知名称",
      "analysis": "API错误(403)"
    },
    {
      "symbol": "000688",
      "price": 33.38,
      "change_pct": 3.47,
      "volume": 320972,
      "rsi": 41.37,
      "ma20": 39.16,
      "last_5_days": [
        34.62,
        35.98,
        33.69,
        32.26,
        33.38
      ],
      "volume_price_signal": "价涨量增（趋势健康）",
      "main_force_signal": "震荡整理（方向待明）",
      "name": "未知名称",
      "analysis": "API错误(403)"
    },
    {
      "symbol": "899050",
      "price": 1226.34,
      "change_pct": -3.2,
      "volume": 7963041,
      "rsi": 33.35,
      "ma20": 1271.39,
      "last_5_days": [
        1281.21,
        1295.95,
        1277.69,
        1266.9,
        1226.34
      ],
      "volume_price_signal": "价跌量缩（抛压减轻）",
      "main_force_signal": "震荡整理（方向待明）",
      "name": "未知名称",
      "analysis": "API错误(403)"
    }
  ]
}